e2e_similarity/__init__.py
e2e_similarity/calculate-similarity.py
e2e_similarity/run_commands.py
e2e_similarity-0.1.dist-info/METADATA
e2e_similarity-0.1.dist-info/WHEEL
e2e_similarity-0.1.dist-info/entry_points.txt
e2e_similarity-0.1.dist-info/top_level.txt
e2e_similarity-0.1.dist-info/RECORD
