Metadata-Version: 2.1
Name: e2e-similarity
Version: 0.1
Summary: This is a package that utilizes OpenAI's powerful davinci-003 model to run Cypress tests, gather and parse the logs, and generate a comprehensive report. Users can specify their test directory when running the command. The package is designed to help developers automate their testing process and gain insights from the test logs.
Requires-Dist: openai
Requires-Dist: rich
